{
  "title": "Interaktív Fizika Gyűjtemény",
  "subject": "fizika",
  "grade": 8,
  "category": "premium_course",
  "description": "Digitális segédlet és gyakorlórendszer általános iskolásoknak, évfolyamonkénti és összesített képletgyűjteményekkel, valamint év végi felmérőkkel.",
  "content": {
    "subtitle": "Digitális segédlet és gyakorlórendszer általános iskolásoknak",
    "sections": [
      {
        "sectionTitle": "Tananyagok Évfolyamok Szerint",
        "cards": [
          { "grade": "6.", "text": "Osztály", "link": "Fizikakepletek_6_osztaly.html" },
          { "grade": "7.", "text": "Osztály", "link": "Fizikakepletek_7_osztaly.html" },
          { "grade": "8.", "text": "Osztály", "link": "Fizikakepletek_8_osztaly.html" }
        ]
      }
    ]
  },
  "questions": []
}